LICENSE
README.md
setup.py
brownian_motion_generator/__init__.py
brownian_motion_generator/brownian_motion_generator_module.py
brownian_motion_generator.egg-info/PKG-INFO
brownian_motion_generator.egg-info/SOURCES.txt
brownian_motion_generator.egg-info/dependency_links.txt
brownian_motion_generator.egg-info/requires.txt
brownian_motion_generator.egg-info/top_level.txt